LICENSE
MANIFEST.in
README.rst
setup.py
sql_server/__init__.py
sql_server/pyodbc/__init__.py
sql_server/pyodbc/base.py
sql_server/pyodbc/client.py
sql_server/pyodbc/compiler.py
sql_server/pyodbc/creation.py
sql_server/pyodbc/features.py
sql_server/pyodbc/introspection.py
sql_server/pyodbc/operations.py
sql_server/pyodbc/schema.py
zipline_django_pyodbc_azure.egg-info/PKG-INFO
zipline_django_pyodbc_azure.egg-info/SOURCES.txt
zipline_django_pyodbc_azure.egg-info/dependency_links.txt
zipline_django_pyodbc_azure.egg-info/requires.txt
zipline_django_pyodbc_azure.egg-info/top_level.txt