Metadata-Version: 1.1
Name: zipline-django-pyodbc-azure
Version: 1.9.12.0
Summary: Django backend for Microsoft SQL Server using pyodbc forked from django-pyodbc-azure
Home-page: https://github.com/neerajaanil/zipline-django-pyodbc-azure
Author: Neeraja
Author-email: neeraja.anil2012@gmail.com
License: BSD
Keywords: azure django
Platform: UNKNOWN
Classifier: Development Status :: 4 - Beta
Classifier: License :: OSI Approved :: BSD License
Classifier: Framework :: Django
Classifier: Programming Language :: Python
Classifier: Programming Language :: Python :: 3
Classifier: Programming Language :: Python :: 3.5
Classifier: Programming Language :: Python :: 3.6
Classifier: Programming Language :: Python :: 3.7
Classifier: Topic :: Internet :: WWW/HTTP
